napari_musa/Widget_DataManager.py
napari_musa/Widgets_DataVisualization.py
napari_musa/Widgets_EndmembersExtraction.py
napari_musa/Widgets_Fusion.py
napari_musa/Widgets_NMF.py
napari_musa/Widgets_PCA.py
napari_musa/Widgets_UMAP.py
napari_musa/_version.py
napari_musa/main.py
napari_musa/napari.yaml
napari_musa/modules/D_illuminants.mat
napari_musa/modules/data.py
napari_musa/modules/functions.py
napari_musa/modules/plot.py
napari_musa-1.0.0.dist-info/licenses/LICENSE
napari_musa-1.0.0.dist-info/METADATA
napari_musa-1.0.0.dist-info/WHEEL
napari_musa-1.0.0.dist-info/entry_points.txt
napari_musa-1.0.0.dist-info/top_level.txt
napari_musa-1.0.0.dist-info/RECORD
