Metadata-Version: 2.4
Name: napari-musa
Version: 1.0.0
Summary: A Napari plugin to perform analysis on Hyperspectral Imaging datasets
Author: Alessia Di Benedetto
Author-email: alessia.dibenedetto@polimi.it
License: 
Project-URL: Bug Tracker, https://github.com/hyperpolimi/napari-musa/issues
Project-URL: Documentation, https://github.com/hyperpolimi/napari-musa#README.md
Project-URL: Source Code, https://github.com/hyperpolimi/napari-musa
Project-URL: User Support, https://github.com/hyperpolimi/napari-musa/issues
Classifier: Development Status :: 2 - Pre-Alpha
Classifier: Framework :: napari
Classifier: Intended Audience :: Developers
Classifier: License :: OSI Approved :: BSD License
Classifier: Operating System :: OS Independent
Classifier: Programming Language :: Python
Classifier: Programming Language :: Python :: 3
Classifier: Programming Language :: Python :: 3 :: Only
Classifier: Programming Language :: Python :: 3.10
Classifier: Programming Language :: Python :: 3.11
Classifier: Programming Language :: Python :: 3.12
Classifier: Programming Language :: Python :: 3.13
Classifier: Topic :: Scientific/Engineering :: Image Processing
Requires-Python: >=3.10
License-File: LICENSE
Requires-Dist: numpy
Requires-Dist: magicgui
Requires-Dist: qtpy
Requires-Dist: scikit-image
Requires-Dist: scikit-learn
Requires-Dist: h5py
Requires-Dist: bokeh
Requires-Dist: plotly
Requires-Dist: PyWavelets
Requires-Dist: scipy
Requires-Dist: pyqtgraph
Requires-Dist: qtawesome
Requires-Dist: matplotlib
Requires-Dist: umap-learn
Requires-Dist: spectral
Requires-Dist: pybaselines
Requires-Dist: pysptools
Requires-Dist: pillow
Provides-Extra: all
Requires-Dist: napari[all]; extra == "all"
Dynamic: license-file
